RVA_greeting_message/__init__.py
RVA_greeting_message/samcode.py
rva_greeting_message-0.1.0.dist-info/METADATA
rva_greeting_message-0.1.0.dist-info/WHEEL
rva_greeting_message-0.1.0.dist-info/top_level.txt
rva_greeting_message-0.1.0.dist-info/RECORD
